MANIFEST.in
README.md
requirements.txt
setup.cfg
setup.py
redis_task_queue/__init__.py
redis_task_queue.egg-info/PKG-INFO
redis_task_queue.egg-info/SOURCES.txt
redis_task_queue.egg-info/dependency_links.txt
redis_task_queue.egg-info/requires.txt
redis_task_queue.egg-info/top_level.txt