Metadata-Version: 1.1
Name: redis-task-queue
Version: 0.0.6
Summary: A python package that can be installed with pip.
Home-page: https://github.com/apegadoboureghida/redis-task-queue
Author: Andres Pegado
Author-email: andres@enodoinc.com
License: BSD
Download-URL: https://github.com/apegadoboureghida/redis-task-queue/tarball/0.0.6
Platform: UNKNOWN
Classifier: Development Status :: 3 - Alpha
Classifier: Intended Audience :: Developers
Classifier: Programming Language :: Python :: 2.7
